shear_bias/__init__.py
shear_bias/data.py
shear_bias/errors.py
shear_bias/info.py
shear_bias/misc.py
shear_bias/plot.py
shear_bias/shapes.py
shear_bias/simulations.py
shear_bias-0.4.dist-info/METADATA
shear_bias-0.4.dist-info/WHEEL
shear_bias-0.4.dist-info/top_level.txt
shear_bias-0.4.dist-info/RECORD
