Metadata-Version: 2.1
Name: shear-bias
Version: 0.4
Summary: Shear bias estimation tools
Home-page: https://github.com/cosmostat/shear_bias
Author: Martin Kilbinger, Arnau Pujol
Author-email: martin.kilbinger@cea.fr
License: GNU GPLv3
Platform: posix
Platform: mac os
Classifier: Programming Language :: Python
Classifier: Natural Language :: English
